[
  {
    "uid": "nicholas.crow@email.com",
    "month_year": "01_23",
    "confirmedEffort": 50,
    "tentativeEffort": 0,
    "notes": "Scouting",
    "name": "Nicholas Crow",
    "company": "it",
    "crew": "moon"
  },
  {
    "uid": "nicholas.crow@email.com",
    "month_year": "02_23",
    "confirmedEffort": 50,
    "tentativeEffort": 30,
    "notes": "Scouting + Carimali",
    "name": "Nicholas Crow",
    "company": "it",
    "crew": "moon"
  },
  {
    "uid": "george.python@email.com",
    "month_year": "01_23",
    "confirmedEffort": 80,
    "tentativeEffort": 0,
    "notes": "Moovtech",
    "name": "Nicholas Crow",
    "company": "us",
    "crew": "sun"
  },
  {
    "uid": "george.python@email.com",
    "month_year": "02_23",
    "confirmedEffort": 50,
    "tentativeEffort": 0,
    "notes": "Moovtech",
    "name": "Nicholas Crow",
    "company": "us",
    "crew": "sun"
  }
]